lced_connectors/__init__.py
lced_connectors/connect.py
lced_exceptions/__init__.py
lced_exceptions/frame_exception.py
lced_exceptions/status_code.py
lced_mqtt/__init__.py
lced_mqtt/base_handler.py
lced_mqtt/loader.py
lced_mqtt/routes.py
lced_utils/__init__.py
lced_utils/buffer_utils.py
lced_utils/data_utils.py
lced_utils/date_time_utils.py
lced_utils/encryption_utils.py
lced_utils/file_utils.py
lced_utils/logger_utils.py
lced_utils/parser_utils.py
lced_utils/request_utils.py
lced_utils/str_utils.py
lced_utils/url_utils.py
lced_utils/uuid_utils.py
lced_variables/__init__.py
lced_variables/dict_var.py
lced_variables-0.0.4.dist-info/METADATA
lced_variables-0.0.4.dist-info/WHEEL
lced_variables-0.0.4.dist-info/top_level.txt
lced_variables-0.0.4.dist-info/RECORD
