Metadata-Version: 2.1
Name: lced_variables
Version: 0.0.4
Summary: lced_variables
Home-page: 
Author: linwanlong
Author-email: linwanlong88@gmail.com
Classifier: Programming Language :: Python :: 3
Classifier: License :: OSI Approved :: MIT License
Classifier: Operating System :: OS Independent
Requires-Python: >=3.10
